symai/TERMS_OF_SERVICE.md
symai/__init__.py
symai/chat.py
symai/components.py
symai/constraints.py
symai/context.py
symai/core.py
symai/core_ext.py
symai/exceptions.py
symai/functional.py
symai/imports.py
symai/interfaces.py
symai/memory.py
symai/post_processors.py
symai/pre_processors.py
symai/processor.py
symai/prompts.py
symai/shell.py
symai/shellsv.py
symai/strategy.py
symai/symbol.py
symai/symsh.md
symai/utils.py
symai/backend/__init__.py
symai/backend/base.py
symai/backend/settings.py
symai/backend/driver/webclient.py
symai/backend/engines/__init__.py
symai/backend/engines/crawler/engine_selenium.py
symai/backend/engines/drawing/engine_bfl.py
symai/backend/engines/drawing/engine_dall_e.py
symai/backend/engines/drawing/engine_gpt_image.py
symai/backend/engines/embedding/engine_llama_cpp.py
symai/backend/engines/embedding/engine_openai.py
symai/backend/engines/embedding/engine_plugin_embeddings.py
symai/backend/engines/execute/engine_python.py
symai/backend/engines/experiments/engine_bard_wrapper.py
symai/backend/engines/experiments/engine_gptfinetuner.py
symai/backend/engines/experiments/engine_llamacpp_completion.py
symai/backend/engines/files/engine_io.py
symai/backend/engines/imagecaptioning/engine_blip2.py
symai/backend/engines/imagecaptioning/engine_llavacpp_client.py
symai/backend/engines/index/engine_pinecone.py
symai/backend/engines/index/engine_qdrant.py
symai/backend/engines/index/engine_vectordb.py
symai/backend/engines/lean/engine_lean4.py
symai/backend/engines/neurosymbolic/__init__.py
symai/backend/engines/neurosymbolic/engine_anthropic_claudeX_chat.py
symai/backend/engines/neurosymbolic/engine_anthropic_claudeX_reasoning.py
symai/backend/engines/neurosymbolic/engine_cerebras.py
symai/backend/engines/neurosymbolic/engine_deepseekX_reasoning.py
symai/backend/engines/neurosymbolic/engine_google_geminiX_reasoning.py
symai/backend/engines/neurosymbolic/engine_groq.py
symai/backend/engines/neurosymbolic/engine_huggingface.py
symbolicai-1.5.0.dist-info/licenses/LICENSE
symbolicai-1.5.0.dist-info/METADATA
symbolicai-1.5.0.dist-info/WHEEL
symbolicai-1.5.0.dist-info/entry_points.txt
symbolicai-1.5.0.dist-info/top_level.txt
symbolicai-1.5.0.dist-info/RECORD
