Metadata-Version: 2.4
Name: symbolicai
Version: 1.5.0
Summary: A Neurosymbolic Perspective on Large Language Models
Author-email: Marius-Constantin Dinu <marius@extensity.ai>, Leoveanu-Condrei Claudiu <leo@extensity.ai>
License: BSD 3-Clause License
Project-URL: Homepage, https://extensity.ai
Project-URL: GitHub, https://github.com/ExtensityAI/symbolicai
Keywords: probabilistic programming,machine learning
Classifier: Programming Language :: Python :: 3
Classifier: License :: OSI Approved :: BSD License
Classifier: Operating System :: OS Independent
Requires-Python: >=3.10
License-File: LICENSE
Requires-Dist: attrs>=23.2.0
Requires-Dist: setuptools>=70.0.0
Requires-Dist: toml>=0.10.2
Requires-Dist: loguru>=0.7.3
Requires-Dist: aiohttp>=3.11.13
Requires-Dist: natsort>=8.3.1
Requires-Dist: numpy<=2.1.3,>=1.26.4
Requires-Dist: tqdm>=4.66.3
Requires-Dist: python-box>=7.1.1
Requires-Dist: pandas>=2.2.2
Requires-Dist: scikit-learn>=1.5.0
Requires-Dist: torch>=2.2.2
Requires-Dist: torchaudio>=2.2.2
Requires-Dist: torchvision>=0.17.2
Requires-Dist: PyYAML>=6.0.1
Requires-Dist: sympy>=1.12
Requires-Dist: openai>=1.60.0
Requires-Dist: anthropic>=0.43.1
Requires-Dist: google-genai>=1.16.1
Requires-Dist: pypdf>=4.3.0
Requires-Dist: ipython>=8.24.0
Requires-Dist: sentencepiece>=0.2.0
Requires-Dist: sentence-transformers>=2.5.1
Requires-Dist: tiktoken>=0.8.0
Requires-Dist: tika>=2.6.0
Requires-Dist: colorama>=0.4.6
Requires-Dist: GitPython>=3.1.42
Requires-Dist: pathos>=0.3.2
Requires-Dist: prompt-toolkit>=3.0.43
Requires-Dist: pydub>=0.25.1
Requires-Dist: opencv-python>=4.8.1.78
Requires-Dist: pymongo<4.8,>=3.12.3
Requires-Dist: requests-toolbelt>=1.0.0
Requires-Dist: pyvis>=0.3.2
Requires-Dist: beartype>=0.18.2
Requires-Dist: pydantic>=2.8.2
Requires-Dist: pydantic-core>=2.20.1
Requires-Dist: pydantic-settings>=2.3.4
Requires-Dist: pycryptodome>=3.20.0
Requires-Dist: httpx>=0.27.2
Requires-Dist: nest-asyncio>=1.6.0
Requires-Dist: rich>=13.9.4
Requires-Dist: playwright>=1.55.0
Requires-Dist: llvmlite>=0.45.1
Requires-Dist: cerebras-cloud-sdk>=1.59.0
Provides-Extra: bitsandbytes
Requires-Dist: bitsandbytes>=0.43.1; extra == "bitsandbytes"
Provides-Extra: blip2
Requires-Dist: decord>=0.6.0; extra == "blip2"
Requires-Dist: salesforce-lavis>=1.0.0; extra == "blip2"
Requires-Dist: opencv-python-headless>=4.5.5.64; extra == "blip2"
Provides-Extra: hf
Requires-Dist: transformers>=4.45.2; extra == "hf"
Requires-Dist: accelerate>=0.33.0; extra == "hf"
Requires-Dist: peft>=0.13.1; extra == "hf"
Requires-Dist: datasets>=3.0.1; extra == "hf"
Requires-Dist: trl>=0.11.3; extra == "hf"
Provides-Extra: scrape
Requires-Dist: beautifulsoup4>=4.12.3; extra == "scrape"
Requires-Dist: trafilatura>=2.0.0; extra == "scrape"
Requires-Dist: pdfminer.six; extra == "scrape"
Requires-Dist: playwright>=1.45.0; extra == "scrape"
Requires-Dist: parallel-web>=0.3.3; extra == "scrape"
Provides-Extra: llama-cpp
Requires-Dist: llama-cpp-python[server]>=0.3.7; extra == "llama-cpp"
Provides-Extra: wolframalpha
Requires-Dist: wolframalpha>=5.0.0; extra == "wolframalpha"
Provides-Extra: whisper
Requires-Dist: openai-whisper>=20240930; extra == "whisper"
Requires-Dist: numba>=0.62.1; extra == "whisper"
Requires-Dist: llvmlite>=0.45.1; extra == "whisper"
Provides-Extra: search
Requires-Dist: firecrawl-py>=4.12.0; extra == "search"
Requires-Dist: parallel-web>=0.3.3; extra == "search"
Provides-Extra: serpapi
Requires-Dist: google_search_results>=2.4.2; extra == "serpapi"
Provides-Extra: services
Requires-Dist: fastapi>=0.110.0; extra == "services"
Requires-Dist: redis>=5.0.2; extra == "services"
Requires-Dist: uvicorn>=0.27.1; extra == "services"
Provides-Extra: solver
Requires-Dist: z3-solver>=4.12.6.0; extra == "solver"
Provides-Extra: qdrant
Requires-Dist: qdrant-client; extra == "qdrant"
Requires-Dist: chonkie[all]>=0.4.1; extra == "qdrant"
Requires-Dist: tokenizers; extra == "qdrant"
Provides-Extra: all
Requires-Dist: symbolicai[hf]; extra == "all"
Requires-Dist: symbolicai[wolframalpha]; extra == "all"
Requires-Dist: symbolicai[whisper]; extra == "all"
Requires-Dist: symbolicai[scrape]; extra == "all"
Requires-Dist: symbolicai[search]; extra == "all"
Requires-Dist: symbolicai[serpapi]; extra == "all"
Requires-Dist: symbolicai[services]; extra == "all"
Requires-Dist: symbolicai[solver]; extra == "all"
Requires-Dist: symbolicai[qdrant]; extra == "all"
Provides-Extra: dev
Requires-Dist: pytest-asyncio>=1.3.0; extra == "dev"
Dynamic: license-file
